{"/about/":"https://librarycarpentry.org/","/advisory/":"https://librarycarpentry.org/governance/","/blog/archive/":"https://carpentries.org/blog/","/audience/":"https://librarycarpentry.org/","/posts-by-authors/":"https://carpentries.org/blog/","/posts-by-tags/":"https://carpentries.org/blog/","/cac/":"https://carpentries.org/curriculum-advisors/","/contact/":"https://carpentries.org/contact/","/events/":"https://carpentries.org/community/#community-events","/get_involved/":"https://carpentries.org/community/","/blog/":"https://carpentries.org/blog/","/instructors/":"https://carpentries.org/instructors","/maintainers/":"https://librarycarpentry.org/lessons/","/our-stories/":"https://carpentries.org","/supporters/":"https://carpentries.org/supporters/","/team/":"https://librarycarpentry.org/governance/","/timeline/":"https://carpentries.org","/workshops/":"https://carpentries.org/workshops/"}